consoleplusplus/__init__.py
core/__init__.py
consoleplusplus-0.1.0.1.dist-info/LICENSE
consoleplusplus-0.1.0.1.dist-info/METADATA
consoleplusplus-0.1.0.1.dist-info/WHEEL
consoleplusplus-0.1.0.1.dist-info/top_level.txt
consoleplusplus-0.1.0.1.dist-info/RECORD
