Metadata-Version: 2.1
Name: consoleplusplus
Version: 0.1.0.1
Summary: A game engine... for the console
Home-page: https://github.com/CodeScratcher/consoleplusplus
Author: skiscratcher
Author-email: email@skiscratcher.com
License: UNKNOWN
Project-URL: Bug Tracker, https://github.com/CodeScratcher/consoleplusplus/issues
Platform: UNKNOWN
Classifier: Programming Language :: Python :: 3
Classifier: License :: OSI Approved :: MIT License
Classifier: Operating System :: OS Independent
Requires-Python: >=3.6
